service/__init__.py
service/__main__.py
service/__version__.py
service/parser.py
service/comparator_service/__init__.py
service/comparator_service/base_comparator.py
service/config/__init__.py
service/config/key_config.py
service/controller/__init__.py
service/controller/api.py
service/generator_service/__init__.py
service/generator_service/auth_generator.py
service/generator_service/base_generator.py
service/generator_service/data_generator.py
service/generator_service/header_generator.py
service/generator_service/payload_generator.py
service/parser_service/__init__.py
service/parser_service/base_parser.py
service/parser_service/swagger_v2.py
service/parser_service/swagger_v3.py
service/strategy/__init__.py
service/strategy/base_strategy.py
service/template_service/__init__.py
service/template_service/auth_templates.py
service/template_service/flow_scenario_templates.py
service/template_service/header_manager_templates.py
service/template_service/helpers_templates.py
service/template_service/locustfile_templates.py
service/template_service/request_helper_templates.py
service/template_service/request_template.py
service/template_service/testdata_templates.py
service/utils/__init__.py
service/utils/logger.py
service/utils/utils.py
tests/__init__.py
automation_sniper-2.4.2.dist-info/LICENSE
automation_sniper-2.4.2.dist-info/METADATA
automation_sniper-2.4.2.dist-info/WHEEL
automation_sniper-2.4.2.dist-info/entry_points.txt
automation_sniper-2.4.2.dist-info/top_level.txt
automation_sniper-2.4.2.dist-info/RECORD
