Metadata-Version: 2.1
Name: automation-sniper
Version: 2.4.2
Summary: Tool to convert Open API / Swagger specifications to automation framework
Home-page: https://github.com/pankajnayak1994/automation-sniper
Author: Pankaj Kumar Nayak
Author-email: nayakpankaj2015@gmail.com
License: Apache-2.0 License
Project-URL: Documentation, https://automation-sniper.readthedocs.io/
Project-URL: Code, https://github.com/pankajnayak1994/automation_sniper
Project-URL: Help/Questions, https://stackoverflow.com/questions/tagged/automation-sniper
Project-URL: Issue tracker, https://github.com/pankajnayak1994/automation_sniper/issues
Platform: UNKNOWN
Classifier: Development Status :: 5 - Production/Stable
Classifier: License :: OSI Approved :: Apache Software License
Classifier: Intended Audience :: Developers
Classifier: Programming Language :: Python :: 3.7
Classifier: Programming Language :: Python :: 3.8
Classifier: Operating System :: OS Independent
Classifier: Topic :: Software Development :: Libraries
Classifier: Topic :: Utilities
Requires-Python: >=3.7
Requires-Dist: Jinja2 (==3.0.3)
Requires-Dist: PyYAML (==6.0)
Requires-Dist: coloredlogs (==14.0)
Requires-Dist: flake8 (==3.8.3)
Requires-Dist: flask (==1.1.2)
Requires-Dist: flask-restful (==0.3.9)
Requires-Dist: pytest (==5.4.3)
Requires-Dist: requests (==2.27.1)
Requires-Dist: validators (==0.18.2)
Requires-Dist: git-changelog (==1.0.0)
